ar_qdk/__init__.py
ar_qdk/main.py
ar_qdk/tests/__init__.py
ar_qdk/tests/main_test.py
ar_one_qdk-1.1.2.dist-info/LICENSE
ar_one_qdk-1.1.2.dist-info/METADATA
ar_one_qdk-1.1.2.dist-info/WHEEL
ar_one_qdk-1.1.2.dist-info/top_level.txt
ar_one_qdk-1.1.2.dist-info/RECORD
