Metadata-Version: 2.1
Name: ar-one-qdk
Version: 1.1.2
Author: PunchyArchy
Author-email: ksmdrmvscthny@gmail.com
License-File: LICENSE
Requires-Dist: qodex-dk ==0.28
